gumo/__init__.py
gumo/core/__init__.py
gumo/core/_configuration.py
gumo/core/application/__init__.py
gumo/core/application/entity_key/__init__.py
gumo/core/domain/__init__.py
gumo/core/domain/configuration/__init__.py
gumo/core/domain/entity_key/__init__.py
gumo/core/domain/entity_key/key.py
gumo/core/exceptions/__init__.py
gumo/core/infrastructure/__init__.py
gumo/core/infrastructure/configuration/__init__.py
gumo/core/infrastructure/credential/__init__.py
gumo/core/injector/__init__.py
gumo_core-0.1.4.dist-info/LICENSE
gumo_core-0.1.4.dist-info/METADATA
gumo_core-0.1.4.dist-info/WHEEL
gumo_core-0.1.4.dist-info/top_level.txt
gumo_core-0.1.4.dist-info/RECORD
