Metadata-Version: 2.1
Name: gumo-core
Version: 0.1.4
Summary: Gumo Core Library
Home-page: https://github.com/gumo-py/gumo-core
Author: Gumo Project Team
Author-email: gumo-py@googlegroups.com
License: UNKNOWN
Platform: UNKNOWN
Classifier: Programming Language :: Python :: 3
Classifier: License :: OSI Approved :: MIT License
Classifier: Operating System :: OS Independent
Requires-Dist: pyyaml (>=5.1)
Requires-Dist: injector (>=0.13.1)
Requires-Dist: google-cloud-storage (>=1.13.0)
Requires-Dist: google-api-python-client (>=1.7.4)
